Test_User_Generator/__init__.py
Test_User_Generator/user_generator.py
Test_User_Generator-1.0.0.dist-info/METADATA
Test_User_Generator-1.0.0.dist-info/WHEEL
Test_User_Generator-1.0.0.dist-info/top_level.txt
Test_User_Generator-1.0.0.dist-info/RECORD
